gitutils/__init__.py
gitutils/__main__.py
gitutils/branch.py
gitutils/email.py
gitutils/find.py
gitutils/git.py
gitutils/pull.py
gitutils/status.py
gitutils/tests/__init__.py
gitutils/tests/conftest.py
gitutils/tests/test_branch.py
gitutils/tests/test_email.py
gitutils/tests/test_find.py
gitutils/tests/test_modified.py
gitutils/tests/test_pull.py
gitutils-1.12.1.dist-info/LICENSE.txt
gitutils-1.12.1.dist-info/METADATA
gitutils-1.12.1.dist-info/WHEEL
gitutils-1.12.1.dist-info/entry_points.txt
gitutils-1.12.1.dist-info/top_level.txt
gitutils-1.12.1.dist-info/RECORD
